{
"meta":{"test_sets":[],"test_metrics":[],"learn_metrics":[{"best_value":"Min","name":"Logloss"}],"launch_mode":"Train","parameters":"","iteration_count":1000,"learn_sets":["learn"],"name":"experiment"},
"iterations":[
{"learn":[0.6785132666],"iteration":0,"passed_time":0.001438801061,"remaining_time":1.43736226},
{"learn":[0.6652618842],"iteration":1,"passed_time":0.002519274386,"remaining_time":1.257117919},
{"learn":[0.6529703558],"iteration":2,"passed_time":0.003601457749,"remaining_time":1.196884458},
{"learn":[0.6377945836],"iteration":3,"passed_time":0.004633540029,"remaining_time":1.153751467},
{"learn":[0.6233029923],"iteration":4,"passed_time":0.005683582698,"remaining_time":1.131032957},
{"learn":[0.6089657737],"iteration":5,"passed_time":0.006702134686,"remaining_time":1.110320313},
{"learn":[0.5954861493],"iteration":6,"passed_time":0.007872079943,"remaining_time":1.116710769},
{"learn":[0.5814206255],"iteration":7,"passed_time":0.008761999155,"remaining_time":1.086487895},
{"learn":[0.5686907377],"iteration":8,"passed_time":0.009920034154,"remaining_time":1.092305983},
{"learn":[0.5549817957],"iteration":9,"passed_time":0.01106426886,"remaining_time":1.095362617},
{"learn":[0.5438283306],"iteration":10,"passed_time":0.0121456122,"remaining_time":1.092000951},
{"learn":[0.5325721881],"iteration":11,"passed_time":0.0132065851,"remaining_time":1.087342174},
{"learn":[0.5225575716],"iteration":12,"passed_time":0.01430488881,"remaining_time":1.086071174},
{"learn":[0.5127195547],"iteration":13,"passed_time":0.01533378103,"remaining_time":1.079936292},
{"learn":[0.502868882],"iteration":14,"passed_time":0.01641019426,"remaining_time":1.077602757},
{"learn":[0.491972178],"iteration":15,"passed_time":0.01749332765,"remaining_time":1.07583965},
{"learn":[0.4823360993],"iteration":16,"passed_time":0.01854135027,"remaining_time":1.072126313},
{"learn":[0.4730970508],"iteration":17,"passed_time":0.01961111337,"remaining_time":1.069895185},
{"learn":[0.463343987],"iteration":18,"passed_time":0.02066255606,"remaining_time":1.066840395},
{"learn":[0.4527731195],"iteration":19,"passed_time":0.02168484813,"remaining_time":1.062557559},
{"learn":[0.4432015383],"iteration":20,"passed_time":0.02284089309,"remaining_time":1.064820683},
{"learn":[0.4323496795],"iteration":21,"passed_time":0.02404516909,"remaining_time":1.068917062},
{"learn":[0.4229178609],"iteration":22,"passed_time":0.02524671503,"remaining_time":1.072436547},
{"learn":[0.4130920305],"iteration":23,"passed_time":0.02639117973,"remaining_time":1.073241309},
{"learn":[0.405841064],"iteration":24,"passed_time":0.0275752353,"remaining_time":1.075434177},
{"learn":[0.3965200886],"iteration":25,"passed_time":0.02869868955,"remaining_time":1.075097062},
{"learn":[0.3885952832],"iteration":26,"passed_time":0.02986935482,"remaining_time":1.076403046},
{"learn":[0.3810309024],"iteration":27,"passed_time":0.03101452954,"remaining_time":1.07664724},
{"learn":[0.3731420643],"iteration":28,"passed_time":0.03219783509,"remaining_time":1.07807234},
{"learn":[0.3666808909],"iteration":29,"passed_time":0.03342149122,"remaining_time":1.080628216},
{"learn":[0.360219411],"iteration":30,"passed_time":0.03461830734,"remaining_time":1.082101284},
{"learn":[0.3531215077],"iteration":31,"passed_time":0.03583394359,"remaining_time":1.083976793},
{"learn":[0.3464622403],"iteration":32,"passed_time":0.03756291063,"remaining_time":1.100707108},
{"learn":[0.3403180295],"iteration":33,"passed_time":0.03901830204,"remaining_time":1.108578817},
{"learn":[0.3331257825],"iteration":34,"passed_time":0.04008738512,"remaining_time":1.105266476},
{"learn":[0.3264107004],"iteration":35,"passed_time":0.04121793953,"remaining_time":1.103724825},
{"learn":[0.3207753098],"iteration":36,"passed_time":0.04229232272,"remaining_time":1.100743427},
{"learn":[0.315651073],"iteration":37,"passed_time":0.0434029267,"remaining_time":1.098779355},
{"learn":[0.3105939337],"iteration":38,"passed_time":0.0445098706,"remaining_time":1.096768863},
{"learn":[0.3050441501],"iteration":39,"passed_time":0.04561156438,"remaining_time":1.094677545},
{"learn":[0.298969284],"iteration":40,"passed_time":0.04663478647,"remaining_time":1.09079903},
{"learn":[0.2929422511],"iteration":41,"passed_time":0.04764970838,"remaining_time":1.086867158},
{"learn":[0.2879834914],"iteration":42,"passed_time":0.04871871146,"remaining_time":1.084274578},
{"learn":[0.2829736845],"iteration":43,"passed_time":0.04982287529,"remaining_time":1.0825152},
{"learn":[0.2775492916],"iteration":44,"passed_time":0.05067707373,"remaining_time":1.07548012},
{"learn":[0.2729501973],"iteration":45,"passed_time":0.05186547939,"remaining_time":1.075644942},
{"learn":[0.2684192252],"iteration":46,"passed_time":0.05304684489,"remaining_time":1.075609429},
{"learn":[0.264043739],"iteration":47,"passed_time":0.05407014698,"remaining_time":1.072391249},
{"learn":[0.259199651],"iteration":48,"passed_time":0.05506410844,"remaining_time":1.068693207},
{"learn":[0.2548791543],"iteration":49,"passed_time":0.05615722233,"remaining_time":1.066987224},
{"learn":[0.2512473021],"iteration":50,"passed_time":0.05735155811,"remaining_time":1.067188797},
{"learn":[0.2481353544],"iteration":51,"passed_time":0.05843069112,"remaining_time":1.065236446},
{"learn":[0.2448477798],"iteration":52,"passed_time":0.05948695421,"remaining_time":1.062908408},
{"learn":[0.2415355593],"iteration":53,"passed_time":0.06065076933,"remaining_time":1.062511626},
{"learn":[0.2382679453],"iteration":54,"passed_time":0.0618950662,"remaining_time":1.063469774},
{"learn":[0.2352111028],"iteration":55,"passed_time":0.06315087331,"remaining_time":1.064543293},
{"learn":[0.2324343341],"iteration":56,"passed_time":0.06433368884,"remaining_time":1.064327519},
{"learn":[0.2286812517],"iteration":57,"passed_time":0.06556111505,"remaining_time":1.064802938},
{"learn":[0.2250063078],"iteration":58,"passed_time":0.06688372389,"remaining_time":1.066738715},
{"learn":[0.2221084603],"iteration":59,"passed_time":0.06800007799,"remaining_time":1.065334555},
{"learn":[0.2187073086],"iteration":60,"passed_time":0.06909657138,"remaining_time":1.063634107},
{"learn":[0.2148084088],"iteration":61,"passed_time":0.07010124307,"remaining_time":1.060563968},
{"learn":[0.2121874952],"iteration":62,"passed_time":0.07111161488,"remaining_time":1.057644177},
{"learn":[0.2095277575],"iteration":63,"passed_time":0.07222603922,"remaining_time":1.056305824},
{"learn":[0.2068270201],"iteration":64,"passed_time":0.07339899454,"remaining_time":1.055816306},
{"learn":[0.2040681422],"iteration":65,"passed_time":0.07457325961,"remaining_time":1.055324613},
{"learn":[0.2005859251],"iteration":66,"passed_time":0.07575151504,"remaining_time":1.054868112},
{"learn":[0.1973286323],"iteration":67,"passed_time":0.07674130641,"remaining_time":1.051807317},
{"learn":[0.1949261485],"iteration":68,"passed_time":0.07773084777,"remaining_time":1.048803178},
{"learn":[0.192646971],"iteration":69,"passed_time":0.07872222918,"remaining_time":1.045881045},
{"learn":[0.1901722558],"iteration":70,"passed_time":0.07986545414,"remaining_time":1.045000097},
{"learn":[0.1878078434],"iteration":71,"passed_time":0.08098185796,"remaining_time":1.043766169},
{"learn":[0.1853568759],"iteration":72,"passed_time":0.0821252095,"remaining_time":1.04287766},
{"learn":[0.1826274106],"iteration":73,"passed_time":0.0831491616,"remaining_time":1.040488157},
{"learn":[0.1802404354],"iteration":74,"passed_time":0.08420166775,"remaining_time":1.038487236},
{"learn":[0.1777164342],"iteration":75,"passed_time":0.08521471962,"remaining_time":1.036031591},
{"learn":[0.175738425],"iteration":76,"passed_time":0.08635160416,"remaining_time":1.035097801},
{"learn":[0.1739865586],"iteration":77,"passed_time":0.08743660759,"remaining_time":1.033545541},
{"learn":[0.1719578074],"iteration":78,"passed_time":0.08866306406,"remaining_time":1.033654203},
{"learn":[0.1700033744],"iteration":79,"passed_time":0.08973110684,"remaining_time":1.031907729},
{"learn":[0.1679448554],"iteration":80,"passed_time":0.09080141994,"remaining_time":1.030203765},
{"learn":[0.1658452479],"iteration":81,"passed_time":0.0919111839,"remaining_time":1.028956912},
{"learn":[0.1644042192],"iteration":82,"passed_time":0.09304268861,"remaining_time":1.02795356},
{"learn":[0.1626524899],"iteration":83,"passed_time":0.09415891242,"remaining_time":1.026780521},
{"learn":[0.1611096394],"iteration":84,"passed_time":0.09495083952,"remaining_time":1.022117861},
{"learn":[0.1596740845],"iteration":85,"passed_time":0.09607874415,"remaining_time":1.021115955},
{"learn":[0.1574295397],"iteration":86,"passed_time":0.09721673872,"remaining_time":1.02021704},
{"learn":[0.1554987757],"iteration":87,"passed_time":0.09830581223,"remaining_time":1.01880569},
{"learn":[0.1533451768],"iteration":88,"passed_time":0.0993324344,"remaining_time":1.016762334},
{"learn":[0.1515039519],"iteration":89,"passed_time":0.1004470285,"remaining_time":1.015631066},
{"learn":[0.149900256],"iteration":90,"passed_time":0.1014708506,"remaining_time":1.013593441},
{"learn":[0.1484090422],"iteration":91,"passed_time":0.1025062929,"remaining_time":1.011692543},
{"learn":[0.146613541],"iteration":92,"passed_time":0.1037360192,"remaining_time":1.011705047},
{"learn":[0.1448431535],"iteration":93,"passed_time":0.1050178468,"remaining_time":1.01219329},
{"learn":[0.1431338845],"iteration":94,"passed_time":0.106214253,"remaining_time":1.011830515},
{"learn":[0.1413446058],"iteration":95,"passed_time":0.1073326171,"remaining_time":1.010715478},
{"learn":[0.139237484],"iteration":96,"passed_time":0.1084122204,"remaining_time":1.009239536},
{"learn":[0.1374961669],"iteration":97,"passed_time":0.1096140861,"remaining_time":1.008896996},
{"learn":[0.1361375563],"iteration":98,"passed_time":0.1106875292,"remaining_time":1.007368322},
{"learn":[0.1344898135],"iteration":99,"passed_time":0.1121253003,"remaining_time":1.009127703},
{"learn":[0.1330334576],"iteration":100,"passed_time":0.1132107237,"remaining_time":1.007687531},
{"learn":[0.131633751],"iteration":101,"passed_time":0.1144307498,"remaining_time":1.007439346},
{"learn":[0.1301929052],"iteration":102,"passed_time":0.1155285838,"remaining_time":1.006108152},
{"learn":[0.1287665835],"iteration":103,"passed_time":0.1166883788,"remaining_time":1.005315263},
{"learn":[0.1274469929],"iteration":104,"passed_time":0.1177872125,"remaining_time":1.003995764},
{"learn":[0.1260032465],"iteration":105,"passed_time":0.1190536696,"remaining_time":1.004094157},
{"learn":[0.1247032005],"iteration":106,"passed_time":0.1203043869,"remaining_time":1.004035677},
{"learn":[0.1234144951],"iteration":107,"passed_time":0.1214893724,"remaining_time":1.003412224},
{"learn":[0.1222455372],"iteration":108,"passed_time":0.1230406159,"remaining_time":1.005772374},
{"learn":[0.121307612],"iteration":109,"passed_time":0.1240695681,"remaining_time":1.003835597},
{"learn":[0.120142828],"iteration":110,"passed_time":0.1253003913,"remaining_time":1.003531963},
{"learn":[0.1187822047],"iteration":111,"passed_time":0.1264184054,"remaining_time":1.002317357},
{"learn":[0.118017687],"iteration":112,"passed_time":0.1276061193,"remaining_time":1.001651574},
{"learn":[0.1171246005],"iteration":113,"passed_time":0.1287321688,"remaining_time":1.000497382},
{"learn":[0.1160313149],"iteration":114,"passed_time":0.1297706112,"remaining_time":0.9986694863},
{"learn":[0.114818245],"iteration":115,"passed_time":0.130939563,"remaining_time":0.9978497733},
{"learn":[0.1135345349],"iteration":116,"passed_time":0.1319812286,"remaining_time":0.9960634607},
{"learn":[0.1128694444],"iteration":117,"passed_time":0.1331458741,"remaining_time":0.995208991},
{"learn":[0.1118260799],"iteration":118,"passed_time":0.1341736663,"remaining_time":0.9933361343},
{"learn":[0.1110346995],"iteration":119,"passed_time":0.1353163409,"remaining_time":0.9923198335},
{"learn":[0.1099503158],"iteration":120,"passed_time":0.136537017,"remaining_time":0.9918680822},
{"learn":[0.1088660685],"iteration":121,"passed_time":0.1377206126,"remaining_time":0.9911368674},
{"learn":[0.1079587192],"iteration":122,"passed_time":0.138820466,"remaining_time":0.9898012089},
{"learn":[0.1072536554],"iteration":123,"passed_time":0.1399053794,"remaining_time":0.9883638095},
{"learn":[0.1064074388],"iteration":124,"passed_time":0.1409467322,"remaining_time":0.9866271254},
{"learn":[0.1054346766],"iteration":125,"passed_time":0.1419849846,"remaining_time":0.9848799726},
{"learn":[0.1045210442],"iteration":126,"passed_time":0.1431306193,"remaining_time":0.9838821314},
{"learn":[0.103500488],"iteration":127,"passed_time":0.144224553,"remaining_time":0.982529767},
{"learn":[0.1025811238],"iteration":128,"passed_time":0.1452680055,"remaining_time":0.9808405642},
{"learn":[0.1018263756],"iteration":129,"passed_time":0.1463638791,"remaining_time":0.9795121143},
{"learn":[0.1009645628],"iteration":130,"passed_time":0.1474610325,"remaining_time":0.9781957044},
{"learn":[0.1002306802],"iteration":131,"passed_time":0.148629038,"remaining_time":0.9773485229},
{"learn":[0.09939884474],"iteration":132,"passed_time":0.1497017712,"remaining_time":0.9758754559},
{"learn":[0.09862020483],"iteration":133,"passed_time":0.1510391198,"remaining_time":0.9761184906},
{"learn":[0.09768152616],"iteration":134,"passed_time":0.1522200656,"remaining_time":0.9753359757},
{"learn":[0.09680341153],"iteration":135,"passed_time":0.1535744348,"remaining_time":0.9756493505},
{"learn":[0.09600663418],"iteration":136,"passed_time":0.1546521881,"remaining_time":0.9741959},
{"learn":[0.0952733183],"iteration":137,"passed_time":0.156051858,"remaining_time":0.9747587072},
{"learn":[0.09452474578],"iteration":138,"passed_time":0.1576016515,"remaining_time":0.9762231792},
{"learn":[0.09382337577],"iteration":139,"passed_time":0.1586590343,"remaining_time":0.974619782},
{"learn":[0.092918883],"iteration":140,"passed_time":0.1596783363,"remaining_time":0.9727921339},
{"learn":[0.09238181452],"iteration":141,"passed_time":0.1607000183,"remaining_time":0.9709902517},
{"learn":[0.09165389867],"iteration":142,"passed_time":0.1616895097,"remaining_time":0.9690063624},
{"learn":[0.09092626615],"iteration":143,"passed_time":0.1627093217,"remaining_time":0.9672165236},
{"learn":[0.09020790966],"iteration":144,"passed_time":0.1637361939,"remaining_time":0.9654789364},
{"learn":[0.08939796406],"iteration":145,"passed_time":0.1647493858,"remaining_time":0.9636710647},
{"learn":[0.08868642001],"iteration":146,"passed_time":0.1659456616,"remaining_time":0.96293639},
{"learn":[0.08809730016],"iteration":147,"passed_time":0.1671046369,"remaining_time":0.9619807475},
{"learn":[0.08770735373],"iteration":148,"passed_time":0.1682280611,"remaining_time":0.9608193291},
{"learn":[0.08700426663],"iteration":149,"passed_time":0.1693233348,"remaining_time":0.9594988972},
{"learn":[0.08627793483],"iteration":150,"passed_time":0.1704880502,"remaining_time":0.958571885},
{"learn":[0.08575316602],"iteration":151,"passed_time":0.1716524754,"remaining_time":0.9576401257},
{"learn":[0.08534422252],"iteration":152,"passed_time":0.1727555792,"remaining_time":0.9563658533},
{"learn":[0.08475054617],"iteration":153,"passed_time":0.1738375525,"remaining_time":0.9549777236},
{"learn":[0.08423493744],"iteration":154,"passed_time":0.1750143779,"remaining_time":0.954110641},
{"learn":[0.08361303764],"iteration":155,"passed_time":0.1762407241,"remaining_time":0.9535075075},
{"learn":[0.08289068865],"iteration":156,"passed_time":0.1774376903,"remaining_time":0.9527386808},
{"learn":[0.08211337206],"iteration":157,"passed_time":0.1785288238,"remaining_time":0.9514004408},
{"learn":[0.08146363952],"iteration":158,"passed_time":0.179602587,"remaining_time":0.9499734318},
{"learn":[0.08099668839],"iteration":159,"passed_time":0.1807071408,"remaining_time":0.9487124894},
{"learn":[0.08031821277],"iteration":160,"passed_time":0.1818960765,"remaining_time":0.9478932185},
{"learn":[0.07985099713],"iteration":161,"passed_time":0.1830661218,"remaining_time":0.9469716669},
{"learn":[0.0792625448],"iteration":162,"passed_time":0.1841755957,"remaining_time":0.9457360344},
{"learn":[0.07854196059],"iteration":163,"passed_time":0.1854300728,"remaining_time":0.9452411028},
{"learn":[0.07802074619],"iteration":164,"passed_time":0.1867742718,"remaining_time":0.9451910119},
{"learn":[0.0775175719],"iteration":165,"passed_time":0.1879597471,"remaining_time":0.9443278861},
{"learn":[0.07696964898],"iteration":166,"passed_time":0.1891494128,"remaining_time":0.9434818016},
{"learn":[0.07641502488],"iteration":167,"passed_time":0.1902723639,"remaining_time":0.9423012307},
{"learn":[0.07599099132],"iteration":168,"passed_time":0.1913982782,"remaining_time":0.9411359124},
{"learn":[0.07550572944],"iteration":169,"passed_time":0.1925037555,"remaining_time":0.9398712768},
{"learn":[0.07505140352],"iteration":170,"passed_time":0.1936316398,"remaining_time":0.9387171312},
{"learn":[0.07469496628],"iteration":171,"passed_time":0.1947694344,"remaining_time":0.9376109982},
{"learn":[0.07415929583],"iteration":172,"passed_time":0.1960116712,"remaining_time":0.9370037694},
{"learn":[0.07377779174],"iteration":173,"passed_time":0.1972398512,"remaining_time":0.9363225119},
{"learn":[0.07316851117],"iteration":174,"passed_time":0.1983713456,"remaining_time":0.9351792007},
{"learn":[0.07277863182],"iteration":175,"passed_time":0.1996026019,"remaining_time":0.9345030907},
{"learn":[0.07234032958],"iteration":176,"passed_time":0.2008382986,"remaining_time":0.9338413544},
{"learn":[0.07194774396],"iteration":177,"passed_time":0.2020370647,"remaining_time":0.9330026248},
{"learn":[0.07147211144],"iteration":178,"passed_time":0.2032163402,"remaining_time":0.9320704765},
{"learn":[0.07109421083],"iteration":179,"passed_time":0.2042978733,"remaining_time":0.9306903115},
{"learn":[0.07081017102],"iteration":180,"passed_time":0.2054788387,"remaining_time":0.9297633643},
{"learn":[0.07043766597],"iteration":181,"passed_time":0.206635574,"remaining_time":0.9287247227},
{"learn":[0.07009227147],"iteration":182,"passed_time":0.2078102791,"remaining_time":0.9277650164},
{"learn":[0.06965388179],"iteration":183,"passed_time":0.2090293954,"remaining_time":0.9269999274},
{"learn":[0.06930893656],"iteration":184,"passed_time":0.2101581798,"remaining_time":0.9258319811},
{"learn":[0.06901703412],"iteration":185,"passed_time":0.2113182945,"remaining_time":0.9248015685},
{"learn":[0.06864963921],"iteration":186,"passed_time":0.2127554558,"remaining_time":0.9249742545},
{"learn":[0.06807613221],"iteration":187,"passed_time":0.2139567918,"remaining_time":0.9241112496},
{"learn":[0.06759140911],"iteration":188,"passed_time":0.215046005,"remaining_time":0.9227635453},
{"learn":[0.06715352107],"iteration":189,"passed_time":0.2161678995,"remaining_time":0.9215578874},
{"learn":[0.0667543973],"iteration":190,"passed_time":0.2172673332,"remaining_time":0.9202579717},
{"learn":[0.06637634652],"iteration":191,"passed_time":0.2184244882,"remaining_time":0.9192030546},
{"learn":[0.0659360027],"iteration":192,"passed_time":0.2194588506,"remaining_time":0.9176336393},
{"learn":[0.06548838454],"iteration":193,"passed_time":0.2205584843,"remaining_time":0.9163409193},
{"learn":[0.06507512781],"iteration":194,"passed_time":0.2215838764,"remaining_time":0.914743695},
{"learn":[0.06471523852],"iteration":195,"passed_time":0.22267571,"remaining_time":0.9134248512},
{"learn":[0.06445715782],"iteration":196,"passed_time":0.223831615,"remaining_time":0.9123694762},
{"learn":[0.06413227723],"iteration":197,"passed_time":0.22499054,"remaining_time":0.9113253185},
{"learn":[0.06372308286],"iteration":198,"passed_time":0.2261470149,"remaining_time":0.9102701455},
{"learn":[0.06343893998],"iteration":199,"passed_time":0.2272773393,"remaining_time":0.9091093573},
{"learn":[0.06322190111],"iteration":200,"passed_time":0.2285194162,"remaining_time":0.908393102},
{"learn":[0.06293613961],"iteration":201,"passed_time":0.2296595405,"remaining_time":0.9072688777},
{"learn":[0.06260252404],"iteration":202,"passed_time":0.2312265743,"remaining_time":0.9078205898},
{"learn":[0.06222063582],"iteration":203,"passed_time":0.2328593698,"remaining_time":0.9086081294},
{"learn":[0.06188761334],"iteration":204,"passed_time":0.2339052224,"remaining_time":0.9070958626},
{"learn":[0.06149918636],"iteration":205,"passed_time":0.2350345365,"remaining_time":0.9059098155},
{"learn":[0.06109305347],"iteration":206,"passed_time":0.2361994919,"remaining_time":0.9048608556},
{"learn":[0.06071337035],"iteration":207,"passed_time":0.2373413263,"remaining_time":0.9037227425},
{"learn":[0.06045252295],"iteration":208,"passed_time":0.2384542203,"remaining_time":0.9024750636},
{"learn":[0.06024174407],"iteration":209,"passed_time":0.2392187271,"remaining_time":0.8999180687},
{"learn":[0.06003610385],"iteration":210,"passed_time":0.2404036727,"remaining_time":0.8989502264},
{"learn":[0.05977186733],"iteration":211,"passed_time":0.2414233147,"remaining_time":0.8973659057},
{"learn":[0.0594783856],"iteration":212,"passed_time":0.2424870077,"remaining_time":0.8959496481},
{"learn":[0.05924544371],"iteration":213,"passed_time":0.2436605833,"remaining_time":0.8949402733},
{"learn":[0.05884536515],"iteration":214,"passed_time":0.2448764296,"remaining_time":0.8940837079},
{"learn":[0.05856365242],"iteration":215,"passed_time":0.2461759873,"remaining_time":0.8935276577},
{"learn":[0.05832616559],"iteration":216,"passed_time":0.2473161519,"remaining_time":0.8923896174},
{"learn":[0.05810895529],"iteration":217,"passed_time":0.2484487764,"remaining_time":0.8912245098},
{"learn":[0.05771302732],"iteration":218,"passed_time":0.2496585825,"remaining_time":0.8903349449},
{"learn":[0.05743230224],"iteration":219,"passed_time":0.2509874109,"remaining_time":0.8898644568},
{"learn":[0.05723492931],"iteration":220,"passed_time":0.2517914051,"remaining_time":0.8875362199},
{"learn":[0.05695485214],"iteration":221,"passed_time":0.2529137125,"remaining_time":0.8863372447},
{"learn":[0.056707046],"iteration":222,"passed_time":0.2540264868,"remaining_time":0.885105741},
{"learn":[0.05644259803],"iteration":223,"passed_time":0.2552122121,"remaining_time":0.8841280205},
{"learn":[0.05617574514],"iteration":224,"passed_time":0.2560339099,"remaining_time":0.8818945784},
{"learn":[0.05586536953],"iteration":225,"passed_time":0.2571576141,"remaining_time":0.880707935},
{"learn":[0.05559534826],"iteration":226,"passed_time":0.258206247,"remaining_time":0.8792662069},
{"learn":[0.05527836547],"iteration":227,"passed_time":0.2593466814,"remaining_time":0.8781387632},
{"learn":[0.05499797325],"iteration":228,"passed_time":0.2606345195,"remaining_time":0.8775074869},
{"learn":[0.05472270597],"iteration":229,"passed_time":0.2618832661,"remaining_time":0.8767396301},
{"learn":[0.05458031281],"iteration":230,"passed_time":0.2629865602,"remaining_time":0.8754833975},
{"learn":[0.05435507117],"iteration":231,"passed_time":0.2641470453,"remaining_time":0.8744178051},
{"learn":[0.05412578929],"iteration":232,"passed_time":0.2652807598,"remaining_time":0.8732632735},
{"learn":[0.05394564898],"iteration":233,"passed_time":0.2663542329,"remaining_time":0.8719117198},
{"learn":[0.05358825907],"iteration":234,"passed_time":0.2674493066,"remaining_time":0.8706328491},
{"learn":[0.05327248048],"iteration":235,"passed_time":0.2684591584,"remaining_time":0.8690796483},
{"learn":[0.0531160575],"iteration":236,"passed_time":0.2695492019,"remaining_time":0.8677892028},
{"learn":[0.05275359325],"iteration":237,"passed_time":0.270678546,"remaining_time":0.8666262691},
{"learn":[0.05251148998],"iteration":238,"passed_time":0.2717995002,"remaining_time":0.8654369023},
{"learn":[0.0522441378],"iteration":239,"passed_time":0.2730365672,"remaining_time":0.8646157961},
{"learn":[0.05204720805],"iteration":240,"passed_time":0.2741928822,"remaining_time":0.8635369193},
{"learn":[0.05182890846],"iteration":241,"passed_time":0.275264245,"remaining_time":0.8621913128},
{"learn":[0.05165723877],"iteration":242,"passed_time":0.2763893096,"remaining_time":0.8610152566},
{"learn":[0.05132956402],"iteration":243,"passed_time":0.2778038201,"remaining_time":0.8607364262},
{"learn":[0.05108101414],"iteration":244,"passed_time":0.2788365021,"remaining_time":0.8592716698},
{"learn":[0.05095950889],"iteration":245,"passed_time":0.2799552263,"remaining_time":0.8580741488},
{"learn":[0.05079752868],"iteration":246,"passed_time":0.2809968388,"remaining_time":0.8566421845},
{"learn":[0.05051873901],"iteration":247,"passed_time":0.2821168229,"remaining_time":0.8554510115},
{"learn":[0.05025667203],"iteration":248,"passed_time":0.2831188146,"remaining_time":0.8539045371},
{"learn":[0.0500256236],"iteration":249,"passed_time":0.2842460189,"remaining_time":0.8527380567},
{"learn":[0.0497868191],"iteration":250,"passed_time":0.2852539807,"remaining_time":0.8512160618},
{"learn":[0.04961883179],"iteration":251,"passed_time":0.2864215659,"remaining_time":0.8501719495},
{"learn":[0.04931151672],"iteration":252,"passed_time":0.2874389078,"remaining_time":0.8486832575},
{"learn":[0.04918365668],"iteration":253,"passed_time":0.2885907124,"remaining_time":0.8475931947},
{"learn":[0.0489614063],"iteration":254,"passed_time":0.2897048465,"remaining_time":0.8463925906},
{"learn":[0.04870570695],"iteration":255,"passed_time":0.2909706441,"remaining_time":0.8456334343},
{"learn":[0.04841472339],"iteration":256,"passed_time":0.2923483335,"remaining_time":0.8451938203},
{"learn":[0.04827216729],"iteration":257,"passed_time":0.2934955886,"remaining_time":0.8440842121},
{"learn":[0.04814393516],"iteration":258,"passed_time":0.2946211894,"remaining_time":0.8429123605},
{"learn":[0.0480781452],"iteration":259,"passed_time":0.2953631086,"remaining_time":0.8406488476},
{"learn":[0.0478693574],"iteration":260,"passed_time":0.2963930608,"remaining_time":0.8392125362},
{"learn":[0.04777007066],"iteration":261,"passed_time":0.2975461657,"remaining_time":0.8381262226},
{"learn":[0.04755336754],"iteration":262,"passed_time":0.2985813781,"remaining_time":0.8367090329},
{"learn":[0.04734953721],"iteration":263,"passed_time":0.2997140425,"remaining_time":0.8355664216},
{"learn":[0.04712761874],"iteration":264,"passed_time":0.3007972025,"remaining_time":0.8342865805},
{"learn":[0.04688307949],"iteration":265,"passed_time":0.3020120884,"remaining_time":0.8333717027},
{"learn":[0.04670012833],"iteration":266,"passed_time":0.3031142422,"remaining_time":0.8321450919},
{"learn":[0.04648832698],"iteration":267,"passed_time":0.3041436447,"remaining_time":0.8307207013},
{"learn":[0.04626706468],"iteration":268,"passed_time":0.3052375283,"remaining_time":0.8294744729},
{"learn":[0.04609128239],"iteration":269,"passed_time":0.3064470842,"remaining_time":0.8285421165},
{"learn":[0.04587246146],"iteration":270,"passed_time":0.3077270621,"remaining_time":0.8277971523},
{"learn":[0.04567686735],"iteration":271,"passed_time":0.308809182,"remaining_time":0.8265186931},
{"learn":[0.04547240708],"iteration":272,"passed_time":0.3102779169,"remaining_time":0.8262712292},
{"learn":[0.04533166137],"iteration":273,"passed_time":0.3112632181,"remaining_time":0.8247339284},
{"learn":[0.04511744457],"iteration":274,"passed_time":0.3124578042,"remaining_time":0.8237523929},
{"learn":[0.0449632517],"iteration":275,"passed_time":0.3136507997,"remaining_time":0.8227651412},
{"learn":[0.04478044959],"iteration":276,"passed_time":0.3146751218,"remaining_time":0.8213361482},
{"learn":[0.044570804],"iteration":277,"passed_time":0.3156857436,"remaining_time":0.8198744852},
{"learn":[0.04444919338],"iteration":278,"passed_time":0.3167651969,"remaining_time":0.8185939318},
{"learn":[0.04431887621],"iteration":279,"passed_time":0.3178665804,"remaining_time":0.8173712068},
{"learn":[0.04408775683],"iteration":280,"passed_time":0.318914253,"remaining_time":0.8160119143},
{"learn":[0.04389753718],"iteration":281,"passed_time":0.3199246548,"remaining_time":0.8145599368},
{"learn":[0.04372774625],"iteration":282,"passed_time":0.3210611594,"remaining_time":0.8134305699},
{"learn":[0.04351441728],"iteration":283,"passed_time":0.3223455668,"remaining_time":0.8126740347},
{"learn":[0.04336210973],"iteration":284,"passed_time":0.3235534729,"remaining_time":0.8117218706},
{"learn":[0.04310595461],"iteration":285,"passed_time":0.3247685991,"remaining_time":0.8107859433},
{"learn":[0.04296982289],"iteration":286,"passed_time":0.3257754309,"remaining_time":0.8093306},
{"learn":[0.04280494695],"iteration":287,"passed_time":0.3267654522,"remaining_time":0.8078368125},
{"learn":[0.04265998123],"iteration":288,"passed_time":0.3279074969,"remaining_time":0.80672052},
{"learn":[0.04251387171],"iteration":289,"passed_time":0.3289247389,"remaining_time":0.8052984986},
{"learn":[0.04235782604],"iteration":290,"passed_time":0.3300040322,"remaining_time":0.8040304426},
{"learn":[0.04222402673],"iteration":291,"passed_time":0.3311958079,"remaining_time":0.8030364109},
{"learn":[0.04204139586],"iteration":292,"passed_time":0.3322113998,"remaining_time":0.8016159033},
{"learn":[0.04193323348],"iteration":293,"passed_time":0.3334831373,"remaining_time":0.800813248},
{"learn":[0.04173929837],"iteration":294,"passed_time":0.3344735086,"remaining_time":0.7993349952},
{"learn":[0.04158966944],"iteration":295,"passed_time":0.3355882227,"remaining_time":0.7981557729},
{"learn":[0.04138194622],"iteration":296,"passed_time":0.336667196,"remaining_time":0.7968923865},
{"learn":[0.04120306485],"iteration":297,"passed_time":0.3377704198,"remaining_time":0.7956873648},
{"learn":[0.04103693712],"iteration":298,"passed_time":0.3390149764,"remaining_time":0.7948143761},
{"learn":[0.04091322568],"iteration":299,"passed_time":0.3402233328,"remaining_time":0.7938544431},
{"learn":[0.04077866582],"iteration":300,"passed_time":0.3415017704,"remaining_time":0.7930556063},
{"learn":[0.0406568244],"iteration":301,"passed_time":0.3427439572,"remaining_time":0.7921698083},
{"learn":[0.04050751991],"iteration":302,"passed_time":0.3439349729,"remaining_time":0.7911639475},
{"learn":[0.04037448593],"iteration":303,"passed_time":0.3450533368,"remaining_time":0.7899905341},
{"learn":[0.04022681334],"iteration":304,"passed_time":0.3462287924,"remaining_time":0.7889475762},
{"learn":[0.040110622],"iteration":305,"passed_time":0.3472256039,"remaining_time":0.7874985919},
{"learn":[0.04000074182],"iteration":306,"passed_time":0.3489169804,"remaining_time":0.7876204151},
{"learn":[0.03986816193],"iteration":307,"passed_time":0.3502154485,"remaining_time":0.7868476959},
{"learn":[0.03973035395],"iteration":308,"passed_time":0.3513393827,"remaining_time":0.7856812734},
{"learn":[0.03962330559],"iteration":309,"passed_time":0.3523607148,"remaining_time":0.7842867523},
{"learn":[0.03945003483],"iteration":310,"passed_time":0.3533946371,"remaining_time":0.782922524},
{"learn":[0.03937547892],"iteration":311,"passed_time":0.3544340995,"remaining_time":0.7815726298},
{"learn":[0.03923180769],"iteration":312,"passed_time":0.3555312332,"remaining_time":0.7803513011},
{"learn":[0.0391200798],"iteration":313,"passed_time":0.3565885561,"remaining_time":0.7790437881},
{"learn":[0.03902646351],"iteration":314,"passed_time":0.3576131482,"remaining_time":0.7776666873},
{"learn":[0.03894551895],"iteration":315,"passed_time":0.3586577107,"remaining_time":0.7763350447},
{"learn":[0.03882509183],"iteration":316,"passed_time":0.3597011133,"remaining_time":0.775002714},
{"learn":[0.03866501065],"iteration":317,"passed_time":0.3607243453,"remaining_time":0.7736289419},
{"learn":[0.03856292163],"iteration":318,"passed_time":0.3617928784,"remaining_time":0.7723540759},
{"learn":[0.0383803971],"iteration":319,"passed_time":0.3628622215,"remaining_time":0.7710822207},
{"learn":[0.03822879607],"iteration":320,"passed_time":0.363948725,"remaining_time":0.769847926},
{"learn":[0.03802704536],"iteration":321,"passed_time":0.3653698156,"remaining_time":0.7693190528},
{"learn":[0.03792686223],"iteration":322,"passed_time":0.3665663749,"remaining_time":0.7683140427},
{"learn":[0.03774293313],"iteration":323,"passed_time":0.3677817308,"remaining_time":0.7673470681},
{"learn":[0.0376327723],"iteration":324,"passed_time":0.3690026072,"remaining_time":0.7663900303},
{"learn":[0.03753255238],"iteration":325,"passed_time":0.3703531566,"remaining_time":0.7656994711},
{"learn":[0.03741751552],"iteration":326,"passed_time":0.3720114724,"remaining_time":0.7656382904},
{"learn":[0.03731263397],"iteration":327,"passed_time":0.3731388368,"remaining_time":0.764479568},
{"learn":[0.03722123606],"iteration":328,"passed_time":0.3743048719,"remaining_time":0.763399906},
{"learn":[0.03714302653],"iteration":329,"passed_time":0.3753786151,"remaining_time":0.7621323398},
{"learn":[0.03705258877],"iteration":330,"passed_time":0.3766500426,"remaining_time":0.7612654939},
{"learn":[0.03697808911],"iteration":331,"passed_time":0.3777896069,"remaining_time":0.7601308958},
{"learn":[0.03682051818],"iteration":332,"passed_time":0.3789955032,"remaining_time":0.7591291311},
{"learn":[0.03666210915],"iteration":333,"passed_time":0.380005975,"remaining_time":0.7577364652},
{"learn":[0.03653650951],"iteration":334,"passed_time":0.3810198769,"remaining_time":0.75635289},
{"learn":[0.03637334186],"iteration":335,"passed_time":0.3821379608,"remaining_time":0.7551773987},
{"learn":[0.03619789154],"iteration":336,"passed_time":0.3832567618,"remaining_time":0.7540036589},
{"learn":[0.03604433168],"iteration":337,"passed_time":0.3843502288,"remaining_time":0.7527806257},
{"learn":[0.03596288614],"iteration":338,"passed_time":0.3856105557,"remaining_time":0.751883709},
{"learn":[0.03586609787],"iteration":339,"passed_time":0.386789478,"remaining_time":0.7508266338},
{"learn":[0.03573591527],"iteration":340,"passed_time":0.3878758246,"remaining_time":0.7495899368},
{"learn":[0.03563037081],"iteration":341,"passed_time":0.3889704583,"remaining_time":0.748370063},
{"learn":[0.03547125582],"iteration":342,"passed_time":0.3901219228,"remaining_time":0.7472597764},
{"learn":[0.03532721634],"iteration":343,"passed_time":0.3911332847,"remaining_time":0.7458820777},
{"learn":[0.0352189114],"iteration":344,"passed_time":0.392341571,"remaining_time":0.744880374},
{"learn":[0.03513528662],"iteration":345,"passed_time":0.3933621431,"remaining_time":0.7435226635},
{"learn":[0.03504665524],"iteration":346,"passed_time":0.3943850952,"remaining_time":0.742171375},
{"learn":[0.03488088189],"iteration":347,"passed_time":0.3955245698,"remaining_time":0.7410402859},
{"learn":[0.03474237496],"iteration":348,"passed_time":0.3965412717,"remaining_time":0.7396801372},
{"learn":[0.03467794498],"iteration":349,"passed_time":0.3977077969,"remaining_time":0.7386001942},
{"learn":[0.03452897317],"iteration":350,"passed_time":0.3987222888,"remaining_time":0.7372386479},
{"learn":[0.03436542441],"iteration":351,"passed_time":0.3997806714,"remaining_time":0.7359598723},
{"learn":[0.03427457943],"iteration":352,"passed_time":0.4009818173,"remaining_time":0.7349440107},
{"learn":[0.0341148268],"iteration":353,"passed_time":0.4023742976,"remaining_time":0.7342762606},
{"learn":[0.03397886718],"iteration":354,"passed_time":0.4035630233,"remaining_time":0.7332342254},
{"learn":[0.03390717076],"iteration":355,"passed_time":0.4046259162,"remaining_time":0.7319637361},
{"learn":[0.03382570907],"iteration":356,"passed_time":0.4061595993,"remaining_time":0.7315423596},
{"learn":[0.03371870096],"iteration":357,"passed_time":0.407393636,"remaining_time":0.7305774143},
{"learn":[0.0336519587],"iteration":358,"passed_time":0.4086327727,"remaining_time":0.7296200761},
{"learn":[0.03356848609],"iteration":359,"passed_time":0.4097601268,"remaining_time":0.7284624476},
{"learn":[0.0334877426],"iteration":360,"passed_time":0.4107563383,"remaining_time":0.7270728537},
{"learn":[0.03341901781],"iteration":361,"passed_time":0.4117761803,"remaining_time":0.7257270802},
{"learn":[0.03334054604],"iteration":362,"passed_time":0.412953386,"remaining_time":0.7246592476},
{"learn":[0.03323953777],"iteration":363,"passed_time":0.4141323015,"remaining_time":0.7235938015},
{"learn":[0.03312595588],"iteration":364,"passed_time":0.4152104347,"remaining_time":0.7223524002},
{"learn":[0.03299709671],"iteration":365,"passed_time":0.4163136786,"remaining_time":0.7211553885},
{"learn":[0.03291055969],"iteration":366,"passed_time":0.4175171148,"remaining_time":0.7201316994},
{"learn":[0.03278077332],"iteration":367,"passed_time":0.418774282,"remaining_time":0.7191993103},
{"learn":[0.0327195283],"iteration":368,"passed_time":0.4197988441,"remaining_time":0.7178674},
{"learn":[0.03259488141],"iteration":369,"passed_time":0.4212685424,"remaining_time":0.7172950857},
{"learn":[0.03249417867],"iteration":370,"passed_time":0.4225789704,"remaining_time":0.716447904},
{"learn":[0.03241232389],"iteration":371,"passed_time":0.4236374932,"remaining_time":0.7151729724},
{"learn":[0.03233725734],"iteration":372,"passed_time":0.4247711277,"remaining_time":0.7140254613},
{"learn":[0.03223205005],"iteration":373,"passed_time":0.4259400032,"remaining_time":0.7129370107},
{"learn":[0.03212994144],"iteration":374,"passed_time":0.4270687073,"remaining_time":0.7117811788},
{"learn":[0.03205237877],"iteration":375,"passed_time":0.428165171,"remaining_time":0.7105719859},
{"learn":[0.03191276831],"iteration":376,"passed_time":0.429312386,"remaining_time":0.7094472586},
{"learn":[0.03180049395],"iteration":377,"passed_time":0.4305104816,"remaining_time":0.7084061364},
{"learn":[0.03172737292],"iteration":378,"passed_time":0.4317371284,"remaining_time":0.7074109676},
{"learn":[0.03161580703],"iteration":379,"passed_time":0.4329226037,"remaining_time":0.706347406},
{"learn":[0.03151896519],"iteration":380,"passed_time":0.434033678,"remaining_time":0.7051623272},
{"learn":[0.03143389021],"iteration":381,"passed_time":0.435240684,"remaining_time":0.7041328343},
{"learn":[0.0313538936],"iteration":382,"passed_time":0.4365943329,"remaining_time":0.7033386512},
{"learn":[0.03128050655],"iteration":383,"passed_time":0.4377673983,"remaining_time":0.7022518681},
{"learn":[0.03115056092],"iteration":384,"passed_time":0.4389948751,"remaining_time":0.7012515537},
{"learn":[0.03108888726],"iteration":385,"passed_time":0.4403552844,"remaining_time":0.7004615146},
{"learn":[0.03100335357],"iteration":386,"passed_time":0.4415130191,"remaining_time":0.6993474954},
{"learn":[0.03093058939],"iteration":387,"passed_time":0.4425692788,"remaining_time":0.6980731923},
{"learn":[0.03080792661],"iteration":388,"passed_time":0.4437896483,"remaining_time":0.6970577766},
{"learn":[0.03072219475],"iteration":389,"passed_time":0.4448758117,"remaining_time":0.6958313978},
{"learn":[0.03067159666],"iteration":390,"passed_time":0.4460085459,"remaining_time":0.6946782722},
{"learn":[0.03053527707],"iteration":391,"passed_time":0.4472145022,"remaining_time":0.6936388198},
{"learn":[0.03041243375],"iteration":392,"passed_time":0.4483693669,"remaining_time":0.6925196073},
{"learn":[0.0302932761],"iteration":393,"passed_time":0.4494963112,"remaining_time":0.6913572705},
{"learn":[0.03024154278],"iteration":394,"passed_time":0.451003384,"remaining_time":0.690777335},
{"learn":[0.03013958018],"iteration":395,"passed_time":0.4521678191,"remaining_time":0.689670108},
{"learn":[0.03002873057],"iteration":396,"passed_time":0.4533831254,"remaining_time":0.6886398605},
{"learn":[0.0299086917],"iteration":397,"passed_time":0.4546280423,"remaining_time":0.687653471},
{"learn":[0.02988795643],"iteration":398,"passed_time":0.4553169737,"remaining_time":0.6858283238},
{"learn":[0.02983668265],"iteration":399,"passed_time":0.4568758708,"remaining_time":0.6853138062},
{"learn":[0.02976678251],"iteration":400,"passed_time":0.4581292678,"remaining_time":0.6843377343},
{"learn":[0.02968129759],"iteration":401,"passed_time":0.4592810724,"remaining_time":0.6832091575},
{"learn":[0.02960421619],"iteration":402,"passed_time":0.4604710984,"remaining_time":0.6821370862},
{"learn":[0.02955793002],"iteration":403,"passed_time":0.4616510139,"remaining_time":0.6810495155},
{"learn":[0.0294341019],"iteration":404,"passed_time":0.4627505676,"remaining_time":0.6798434265},
{"learn":[0.02937267579],"iteration":405,"passed_time":0.4640169347,"remaining_time":0.6788819192},
{"learn":[0.0292852803],"iteration":406,"passed_time":0.4653369834,"remaining_time":0.6779971282},
{"learn":[0.02920911654],"iteration":407,"passed_time":0.4665114688,"remaining_time":0.6768989939},
{"learn":[0.02912721412],"iteration":408,"passed_time":0.4677485052,"remaining_time":0.6758908718},
{"learn":[0.02906392792],"iteration":409,"passed_time":0.46888107,"remaining_time":0.6747312958},
{"learn":[0.02898469952],"iteration":410,"passed_time":0.4700886057,"remaining_time":0.6736792914},
{"learn":[0.02890671728],"iteration":411,"passed_time":0.471154119,"remaining_time":0.6724238398},
{"learn":[0.02883064062],"iteration":412,"passed_time":0.4722333223,"remaining_time":0.6711887656},
{"learn":[0.02876307117],"iteration":413,"passed_time":0.4733326461,"remaining_time":0.6699829241},
{"learn":[0.02871401614],"iteration":414,"passed_time":0.4745424422,"remaining_time":0.6689333221},
{"learn":[0.02859032523],"iteration":415,"passed_time":0.4757763888,"remaining_time":0.6679168535},
{"learn":[0.02853371189],"iteration":416,"passed_time":0.4770783569,"remaining_time":0.6669944414},
{"learn":[0.02846930829],"iteration":417,"passed_time":0.4784643268,"remaining_time":0.6661871728},
{"learn":[0.0283795445],"iteration":418,"passed_time":0.4798515271,"remaining_time":0.6653788478},
{"learn":[0.02825980448],"iteration":419,"passed_time":0.4810238789,"remaining_time":0.6642710709},
{"learn":[0.02816292529],"iteration":420,"passed_time":0.4821059657,"remaining_time":0.663038846},
{"learn":[0.0281031096],"iteration":421,"passed_time":0.4832688608,"remaining_time":0.6619180132},
{"learn":[0.02797422861],"iteration":422,"passed_time":0.4842658124,"remaining_time":0.6605706235},
{"learn":[0.02793652357],"iteration":423,"passed_time":0.4852751842,"remaining_time":0.6592417596},
{"learn":[0.02788167671],"iteration":424,"passed_time":0.4862606954,"remaining_time":0.6578821173},
{"learn":[0.02782796175],"iteration":425,"passed_time":0.4872919277,"remaining_time":0.6565858368},
{"learn":[0.02772061232],"iteration":426,"passed_time":0.4882926193,"remaining_time":0.6552498147},
{"learn":[0.02764503195],"iteration":427,"passed_time":0.4893010211,"remaining_time":0.6539256637},
{"learn":[0.02757189055],"iteration":428,"passed_time":0.4902850623,"remaining_time":0.6525705608},
{"learn":[0.02753394248],"iteration":429,"passed_time":0.4912748737,"remaining_time":0.6512248325},
{"learn":[0.02747730197],"iteration":430,"passed_time":0.4922745653,"remaining_time":0.6498937996},
{"learn":[0.02735718846],"iteration":431,"passed_time":0.4933200944,"remaining_time":0.6486245686},
{"learn":[0.02731995372],"iteration":432,"passed_time":0.4946345525,"remaining_time":0.6477085249},
{"learn":[0.02719682505],"iteration":433,"passed_time":0.4957698073,"remaining_time":0.6465569376},
{"learn":[0.02708749097],"iteration":434,"passed_time":0.496962503,"remaining_time":0.6454800327},
{"learn":[0.02703635761],"iteration":435,"passed_time":0.4980718667,"remaining_time":0.6442948},
{"learn":[0.02695885031],"iteration":436,"passed_time":0.4990784484,"remaining_time":0.6429774976},
{"learn":[0.02689918434],"iteration":437,"passed_time":0.5001079307,"remaining_time":0.6416909978},
{"learn":[0.02684689738],"iteration":438,"passed_time":0.5011065322,"remaining_time":0.6403662063},
{"learn":[0.02677489101],"iteration":439,"passed_time":0.5021080838,"remaining_time":0.6390466521},
{"learn":[0.02669830396],"iteration":440,"passed_time":0.5031410961,"remaining_time":0.6377684189},
{"learn":[0.02659832918],"iteration":441,"passed_time":0.5041356776,"remaining_time":0.6364427785},
{"learn":[0.02649387776],"iteration":442,"passed_time":0.5051591797,"remaining_time":0.6351549957},
{"learn":[0.02643499359],"iteration":443,"passed_time":0.5061581513,"remaining_time":0.6338376849},
{"learn":[0.02639013616],"iteration":444,"passed_time":0.507162753,"remaining_time":0.6325288267},
{"learn":[0.02630947591],"iteration":445,"passed_time":0.5081796049,"remaining_time":0.6312365496},
{"learn":[0.02623558898],"iteration":446,"passed_time":0.5091808265,"remaining_time":0.6299261679},
{"learn":[0.02618165361],"iteration":447,"passed_time":0.510392723,"remaining_time":0.6288767479},
{"learn":[0.02611556112],"iteration":448,"passed_time":0.5116281296,"remaining_time":0.6278554553},
{"learn":[0.02603183583],"iteration":449,"passed_time":0.5126834524,"remaining_time":0.6266131085},
{"learn":[0.02596946451],"iteration":450,"passed_time":0.5137041745,"remaining_time":0.6253294718},
{"learn":[0.02591520352],"iteration":451,"passed_time":0.5147246265,"remaining_time":0.624046671},
{"learn":[0.02583679372],"iteration":452,"passed_time":0.5157479786,"remaining_time":0.6227685304},
{"learn":[0.02578030211],"iteration":453,"passed_time":0.5167671806,"remaining_time":0.6214865211},
{"learn":[0.0256821185],"iteration":454,"passed_time":0.5177767124,"remaining_time":0.6201940841},
{"learn":[0.02561793125],"iteration":455,"passed_time":0.5187825741,"remaining_time":0.6188985094},
{"learn":[0.02555988203],"iteration":456,"passed_time":0.5197867858,"remaining_time":0.6176022422},
{"learn":[0.02546388975],"iteration":457,"passed_time":0.520771467,"remaining_time":0.6162841378},
{"learn":[0.02540844523],"iteration":458,"passed_time":0.5217680885,"remaining_time":0.6149815597},
{"learn":[0.02536062642],"iteration":459,"passed_time":0.5227879706,"remaining_time":0.6137076176},
{"learn":[0.02527609457],"iteration":460,"passed_time":0.5237717518,"remaining_time":0.6123925688},
{"learn":[0.02521173257],"iteration":461,"passed_time":0.5248524951,"remaining_time":0.6111918666},
{"learn":[0.02514999682],"iteration":462,"passed_time":0.5259241183,"remaining_time":0.6099811048},
{"learn":[0.02506876741],"iteration":463,"passed_time":0.5270163016,"remaining_time":0.6087946932},
{"learn":[0.0250206912],"iteration":464,"passed_time":0.528044534,"remaining_time":0.6075351091},
{"learn":[0.02495768912],"iteration":465,"passed_time":0.5290798161,"remaining_time":0.6062845961},
{"learn":[0.02489335039],"iteration":466,"passed_time":0.530127869,"remaining_time":0.6050495807},
{"learn":[0.02483774042],"iteration":467,"passed_time":0.5311561412,"remaining_time":0.6037928785},
{"learn":[0.02481016182],"iteration":468,"passed_time":0.5321915436,"remaining_time":0.6025452231},
{"learn":[0.02472649039],"iteration":469,"passed_time":0.5332010154,"remaining_time":0.6012692301},
{"learn":[0.02469616409],"iteration":470,"passed_time":0.5342325376,"remaining_time":0.6000191346},
{"learn":[0.02461259531],"iteration":471,"passed_time":0.5352619698,"remaining_time":0.5987676273},
{"learn":[0.02454388617],"iteration":472,"passed_time":0.5362921121,"remaining_time":0.59751785},
{"learn":[0.02447836807],"iteration":473,"passed_time":0.5373136741,"remaining_time":0.5962594781},
{"learn":[0.02444312434],"iteration":474,"passed_time":0.5383648068,"remaining_time":0.5950347865},
{"learn":[0.02439306219],"iteration":475,"passed_time":0.5393664585,"remaining_time":0.5937563534},
{"learn":[0.02433394777],"iteration":476,"passed_time":0.5410077539,"remaining_time":0.5931804094},
{"learn":[0.02429656541],"iteration":477,"passed_time":0.5422218698,"remaining_time":0.5921335064},
{"learn":[0.02424612296],"iteration":478,"passed_time":0.5434442265,"remaining_time":0.5910948685},
{"learn":[0.02418432312],"iteration":479,"passed_time":0.5445007993,"remaining_time":0.5898758659},
{"learn":[0.02411321113],"iteration":480,"passed_time":0.5457322359,"remaining_time":0.5888462171},
{"learn":[0.02404612013],"iteration":481,"passed_time":0.5467384376,"remaining_time":0.5875736736},
{"learn":[0.02401549339],"iteration":482,"passed_time":0.547730409,"remaining_time":0.586287001},
{"learn":[0.02396494009],"iteration":483,"passed_time":0.5487353807,"remaining_time":0.5850154059},
{"learn":[0.02391537747],"iteration":484,"passed_time":0.549722512,"remaining_time":0.5837259664},
{"learn":[0.02386392495],"iteration":485,"passed_time":0.5507339539,"remaining_time":0.5824634821},
{"learn":[0.02380004221],"iteration":486,"passed_time":0.5517310054,"remaining_time":0.5811868701},
{"learn":[0.02372102511],"iteration":487,"passed_time":0.5527349971,"remaining_time":0.5799186854},
{"learn":[0.0236546043],"iteration":488,"passed_time":0.553750839,"remaining_time":0.5786639647},
{"learn":[0.02360725188],"iteration":489,"passed_time":0.554815962,"remaining_time":0.5774615114},
{"learn":[0.02355183835],"iteration":490,"passed_time":0.5558800049,"remaining_time":0.576258498},
{"learn":[0.02350761037],"iteration":491,"passed_time":0.556945478,"remaining_time":0.575057526},
{"learn":[0.02346240695],"iteration":492,"passed_time":0.5580305214,"remaining_time":0.5738772299},
{"learn":[0.02340183694],"iteration":493,"passed_time":0.5592384772,"remaining_time":0.5728232175},
{"learn":[0.02332355568],"iteration":494,"passed_time":0.5603914323,"remaining_time":0.5717124714},
{"learn":[0.02327477138],"iteration":495,"passed_time":0.5615968884,"remaining_time":0.5706549027},
{"learn":[0.0232352382],"iteration":496,"passed_time":0.56259819,"remaining_time":0.5693901198},
{"learn":[0.0231716886],"iteration":497,"passed_time":0.5639066382,"remaining_time":0.5684360088},
{"learn":[0.02312197965],"iteration":498,"passed_time":0.5648962296,"remaining_time":0.5671603427},
{"learn":[0.0230407867],"iteration":499,"passed_time":0.5658804908,"remaining_time":0.5658804908},
{"learn":[0.02301860814],"iteration":500,"passed_time":0.5668899826,"remaining_time":0.5646269488},
{"learn":[0.02295900753],"iteration":501,"passed_time":0.5678874142,"remaining_time":0.5633624149},
{"learn":[0.02291034479],"iteration":502,"passed_time":0.568898826,"remaining_time":0.5621127565},
{"learn":[0.02287947755],"iteration":503,"passed_time":0.5699367784,"remaining_time":0.5608901629},
{"learn":[0.02279583393],"iteration":504,"passed_time":0.5709294898,"remaining_time":0.5596239554},
{"learn":[0.02273255529],"iteration":505,"passed_time":0.5719290514,"remaining_time":0.5583655166},
{"learn":[0.02269991569],"iteration":506,"passed_time":0.5730793663,"remaining_time":0.5572546895},
{"learn":[0.02262578189],"iteration":507,"passed_time":0.5742619718,"remaining_time":0.5561749805},
{"learn":[0.02257938654],"iteration":508,"passed_time":0.5753047646,"remaining_time":0.5549599988},
{"learn":[0.02251419962],"iteration":509,"passed_time":0.5763554873,"remaining_time":0.5537533113},
{"learn":[0.02248612041],"iteration":510,"passed_time":0.577361729,"remaining_time":0.5525046682},
{"learn":[0.02245491951],"iteration":511,"passed_time":0.5783447902,"remaining_time":0.5512348782},
{"learn":[0.02241138455],"iteration":512,"passed_time":0.5795024501,"remaining_time":0.5501319555},
{"learn":[0.02233941208],"iteration":513,"passed_time":0.5805520927,"remaining_time":0.5489266869},
{"learn":[0.02230651842],"iteration":514,"passed_time":0.5815469942,"remaining_time":0.5476704703},
{"learn":[0.02223061322],"iteration":515,"passed_time":0.5825436357,"remaining_time":0.5464168986},
{"learn":[0.02218055562],"iteration":516,"passed_time":0.5835507775,"remaining_time":0.5451741306},
{"learn":[0.0221327725],"iteration":517,"passed_time":0.5845390688,"remaining_time":0.543914732},
{"learn":[0.02209058021],"iteration":518,"passed_time":0.5855563707,"remaining_time":0.5426832646},
{"learn":[0.02204650914],"iteration":519,"passed_time":0.586540972,"remaining_time":0.5414224357},
{"learn":[0.021986679],"iteration":520,"passed_time":0.5875524338,"remaining_time":0.5401873624},
{"learn":[0.02190053954],"iteration":521,"passed_time":0.5887347842,"remaining_time":0.53910963},
{"learn":[0.02183950612],"iteration":522,"passed_time":0.5898587688,"remaining_time":0.5379782652},
{"learn":[0.02175241764],"iteration":523,"passed_time":0.5909208517,"remaining_time":0.5367906973},
{"learn":[0.02169207549],"iteration":524,"passed_time":0.5919792145,"remaining_time":0.5356002417},
{"learn":[0.02164473127],"iteration":525,"passed_time":0.5930135169,"remaining_time":0.5343886065},
{"learn":[0.02159558167],"iteration":526,"passed_time":0.5940328689,"remaining_time":0.5331642258},
{"learn":[0.02156462072],"iteration":527,"passed_time":0.5950599211,"remaining_time":0.5319475052},
{"learn":[0.0215101696],"iteration":528,"passed_time":0.5961025036,"remaining_time":0.5307453293},
{"learn":[0.02145410282],"iteration":529,"passed_time":0.5971331758,"remaining_time":0.5295331936},
{"learn":[0.02139787864],"iteration":530,"passed_time":0.598161368,"remaining_time":0.528319551},
{"learn":[0.02132652645],"iteration":531,"passed_time":0.5991842601,"remaining_time":0.5271019431},
{"learn":[0.02128148078],"iteration":532,"passed_time":0.6002173224,"remaining_time":0.5258939767},
{"learn":[0.02124068052],"iteration":533,"passed_time":0.6012874255,"remaining_time":0.5247189893},
{"learn":[0.02121541992],"iteration":534,"passed_time":0.6023161277,"remaining_time":0.5235084101},
{"learn":[0.0211490732],"iteration":535,"passed_time":0.6033358897,"remaining_time":0.5222907702},
{"learn":[0.02109221215],"iteration":536,"passed_time":0.6045150449,"remaining_time":0.5212112957},
{"learn":[0.02103878718],"iteration":537,"passed_time":0.6056223491,"remaining_time":0.5200697496},
{"learn":[0.02096250487],"iteration":538,"passed_time":0.6066777419,"remaining_time":0.5188839313},
{"learn":[0.02090871205],"iteration":539,"passed_time":0.6077448249,"remaining_time":0.5177085545},
{"learn":[0.02088619884],"iteration":540,"passed_time":0.6087815573,"remaining_time":0.5165078277},
{"learn":[0.0208449652],"iteration":541,"passed_time":0.6097698086,"remaining_time":0.5152667386},
{"learn":[0.02076126028],"iteration":542,"passed_time":0.6107781604,"remaining_time":0.5140434978},
{"learn":[0.02068330256],"iteration":543,"passed_time":0.611781542,"remaining_time":0.5128168808},
{"learn":[0.02064363425],"iteration":544,"passed_time":0.6127737235,"remaining_time":0.5115817324},
{"learn":[0.02061289979],"iteration":545,"passed_time":0.6137608148,"remaining_time":0.5103432416},
{"learn":[0.02054453654],"iteration":546,"passed_time":0.6151058538,"remaining_time":0.5094021056},
{"learn":[0.02049304685],"iteration":547,"passed_time":0.6163113798,"remaining_time":0.5083444228},
{"learn":[0.02044280513],"iteration":548,"passed_time":0.6173327419,"remaining_time":0.5071349118},
{"learn":[0.02039623217],"iteration":549,"passed_time":0.618358974,"remaining_time":0.5059300697},
{"learn":[0.02034577734],"iteration":550,"passed_time":0.6193912763,"remaining_time":0.5047308223},
{"learn":[0.02029411435],"iteration":551,"passed_time":0.6204801198,"remaining_time":0.5035780683},
{"learn":[0.02026275635],"iteration":552,"passed_time":0.6215965239,"remaining_time":0.5024478231},
{"learn":[0.02023263319],"iteration":553,"passed_time":0.6226391364,"remaining_time":0.5012582218},
{"learn":[0.02019029662],"iteration":554,"passed_time":0.6236873491,"remaining_time":0.5000736402},
{"learn":[0.02015076381],"iteration":555,"passed_time":0.6247631223,"remaining_time":0.4989115581},
{"learn":[0.02009903508],"iteration":556,"passed_time":0.6257879444,"remaining_time":0.4977092628},
{"learn":[0.02005161059],"iteration":557,"passed_time":0.6268281769,"remaining_time":0.4965198104},
{"learn":[0.01999902116],"iteration":558,"passed_time":0.627852439,"remaining_time":0.4953182926},
{"learn":[0.01993789535],"iteration":559,"passed_time":0.6288860713,"remaining_time":0.4941247703},
{"learn":[0.01988770509],"iteration":560,"passed_time":0.6300058955,"remaining_time":0.4929992658},
{"learn":[0.01985272374],"iteration":561,"passed_time":0.6311485899,"remaining_time":0.4918916056},
{"learn":[0.01980497785],"iteration":562,"passed_time":0.6322497139,"remaining_time":0.4907515541},
{"learn":[0.01974669399],"iteration":563,"passed_time":0.633330987,"remaining_time":0.4895962949},
{"learn":[0.01967615644],"iteration":564,"passed_time":0.6343914999,"remaining_time":0.4884253141},
{"learn":[0.01961117456],"iteration":565,"passed_time":0.6355266447,"remaining_time":0.4873119501},
{"learn":[0.01955565006],"iteration":566,"passed_time":0.6366648289,"remaining_time":0.4862008306},
{"learn":[0.01953216096],"iteration":567,"passed_time":0.6377836834,"remaining_time":0.4850749141},
{"learn":[0.01949036491],"iteration":568,"passed_time":0.6388855072,"remaining_time":0.4839361223},
{"learn":[0.01944955592],"iteration":569,"passed_time":0.6399029691,"remaining_time":0.4827338188},
{"learn":[0.01941389608],"iteration":570,"passed_time":0.6409190411,"remaining_time":0.4815311184},
{"learn":[0.01934768246],"iteration":571,"passed_time":0.6419320329,"remaining_time":0.4803267659},
{"learn":[0.01931702192],"iteration":572,"passed_time":0.6429510549,"remaining_time":0.479127575},
{"learn":[0.01927310587],"iteration":573,"passed_time":0.6439798471,"remaining_time":0.4779362629},
{"learn":[0.01923245539],"iteration":574,"passed_time":0.6450225597,"remaining_time":0.476755805},
{"learn":[0.01919980504],"iteration":575,"passed_time":0.6460324415,"remaining_time":0.4755516583},
{"learn":[0.0191608636],"iteration":576,"passed_time":0.6470662938,"remaining_time":0.4743657578},
{"learn":[0.01911162524],"iteration":577,"passed_time":0.6480926559,"remaining_time":0.4731749149},
{"learn":[0.01907396884],"iteration":578,"passed_time":0.6491232782,"remaining_time":0.4719877377},
{"learn":[0.01902415506],"iteration":579,"passed_time":0.6501701808,"remaining_time":0.4708128895},
{"learn":[0.0189873591],"iteration":580,"passed_time":0.6513300358,"remaining_time":0.4697199398},
{"learn":[0.0189509103],"iteration":581,"passed_time":0.6524928109,"remaining_time":0.4686288573},
{"learn":[0.01890787784],"iteration":582,"passed_time":0.6536147051,"remaining_time":0.4675082882},
{"learn":[0.01887460079],"iteration":583,"passed_time":0.654629657,"remaining_time":0.4663115365},
{"learn":[0.01883163415],"iteration":584,"passed_time":0.655646099,"remaining_time":0.4651164634},
{"learn":[0.01880230566],"iteration":585,"passed_time":0.6566588409,"remaining_time":0.4639193859},
{"learn":[0.01878452672],"iteration":586,"passed_time":0.657684113,"remaining_time":0.4627317524},
{"learn":[0.0187364712],"iteration":587,"passed_time":0.6587071751,"remaining_time":0.4615431227},
{"learn":[0.01868024089],"iteration":588,"passed_time":0.6598833505,"remaining_time":0.4604618965},
{"learn":[0.01864442639],"iteration":589,"passed_time":0.6609442934,"remaining_time":0.4593002717},
{"learn":[0.01862374463],"iteration":590,"passed_time":0.6619893659,"remaining_time":0.4581280045},
{"learn":[0.01858306524],"iteration":591,"passed_time":0.6630408286,"remaining_time":0.4569605711},
{"learn":[0.01855811834],"iteration":592,"passed_time":0.6641151818,"remaining_time":0.4558092395},
{"learn":[0.01851116896],"iteration":593,"passed_time":0.6651741647,"remaining_time":0.4546476614},
{"learn":[0.01847670286],"iteration":594,"passed_time":0.666206397,"remaining_time":0.4534682198},
{"learn":[0.01843563327],"iteration":595,"passed_time":0.6673877422,"remaining_time":0.4523903487},
{"learn":[0.01840833926],"iteration":596,"passed_time":0.6684171344,"remaining_time":0.4512095564},
{"learn":[0.01838240093],"iteration":597,"passed_time":0.6694906476,"remaining_time":0.4500589303},
{"learn":[0.01831274024],"iteration":598,"passed_time":0.6705026694,"remaining_time":0.4488673964},
{"learn":[0.01829156764],"iteration":599,"passed_time":0.671500491,"remaining_time":0.447666994},
{"learn":[0.01826814076],"iteration":600,"passed_time":0.6724903223,"remaining_time":0.4464619611},
{"learn":[0.0182383502],"iteration":601,"passed_time":0.6735082043,"remaining_time":0.4452761882},
{"learn":[0.01820012143],"iteration":602,"passed_time":0.6745622174,"remaining_time":0.44411476},
{"learn":[0.0181690098],"iteration":603,"passed_time":0.6755785393,"remaining_time":0.4429289761},
{"learn":[0.01812903437],"iteration":604,"passed_time":0.6765763608,"remaining_time":0.4417316736},
{"learn":[0.01807959631],"iteration":605,"passed_time":0.6775931128,"remaining_time":0.4405473374},
{"learn":[0.01805176483],"iteration":606,"passed_time":0.6785916043,"remaining_time":0.4393517307},
{"learn":[0.01802033627],"iteration":607,"passed_time":0.6796145464,"remaining_time":0.4381725365},
{"learn":[0.01798043933],"iteration":608,"passed_time":0.6806069879,"remaining_time":0.436974273},
{"learn":[0.01793606774],"iteration":609,"passed_time":0.6816217898,"remaining_time":0.4357909803},
{"learn":[0.01787487822],"iteration":610,"passed_time":0.6827825948,"remaining_time":0.4347011938},
{"learn":[0.0178404743],"iteration":611,"passed_time":0.6839536601,"remaining_time":0.4336176799},
{"learn":[0.01781145083],"iteration":612,"passed_time":0.6849810723,"remaining_time":0.4324431892},
{"learn":[0.01778349158],"iteration":613,"passed_time":0.6860040544,"remaining_time":0.4312663925},
{"learn":[0.01775523511],"iteration":614,"passed_time":0.6870499569,"remaining_time":0.4301044446},
{"learn":[0.01771474102],"iteration":615,"passed_time":0.6880868993,"remaining_time":0.4289372879},
{"learn":[0.0176876648],"iteration":616,"passed_time":0.6891046113,"remaining_time":0.4277586161},
{"learn":[0.01764046743],"iteration":617,"passed_time":0.6902067548,"remaining_time":0.4266326543},
{"learn":[0.01760283666],"iteration":618,"passed_time":0.6912454572,"remaining_time":0.4254677208},
{"learn":[0.01757748323],"iteration":619,"passed_time":0.692252269,"remaining_time":0.4242836487},
{"learn":[0.01752347081],"iteration":620,"passed_time":0.6932634408,"remaining_time":0.4231028085},
{"learn":[0.01750594822],"iteration":621,"passed_time":0.6942693425,"remaining_time":0.421919311},
{"learn":[0.01747402437],"iteration":622,"passed_time":0.6952999248,"remaining_time":0.4207513188},
{"learn":[0.01744549378],"iteration":623,"passed_time":0.6963189068,"remaining_time":0.4195767771},
{"learn":[0.0174117049],"iteration":624,"passed_time":0.6973529291,"remaining_time":0.4184117574},
{"learn":[0.01738625072],"iteration":625,"passed_time":0.6984731735,"remaining_time":0.4172986692},
{"learn":[0.01734820417],"iteration":626,"passed_time":0.699619158,"remaining_time":0.4162008707},
{"learn":[0.01730303875],"iteration":627,"passed_time":0.7006447201,"remaining_time":0.4150315858},
{"learn":[0.01727775828],"iteration":628,"passed_time":0.7016416617,"remaining_time":0.4138458768},
{"learn":[0.0172294519],"iteration":629,"passed_time":0.7027013145,"remaining_time":0.4126975974},
{"learn":[0.01719485379],"iteration":630,"passed_time":0.7036899559,"remaining_time":0.4115080725},
{"learn":[0.01716644291],"iteration":631,"passed_time":0.7046849974,"remaining_time":0.4103229099},
{"learn":[0.01714328829],"iteration":632,"passed_time":0.7056730887,"remaining_time":0.4091343184},
{"learn":[0.01711835676],"iteration":633,"passed_time":0.7067002912,"remaining_time":0.4079689378},
{"learn":[0.01710080297],"iteration":634,"passed_time":0.7075392893,"remaining_time":0.4066958119},
{"learn":[0.01707240758],"iteration":635,"passed_time":0.7085682015,"remaining_time":0.4055327442},
{"learn":[0.01703469291],"iteration":636,"passed_time":0.7096085439,"remaining_time":0.4043766114},
{"learn":[0.0169998304],"iteration":637,"passed_time":0.7106472464,"remaining_time":0.4032199109},
{"learn":[0.01695548045],"iteration":638,"passed_time":0.7116639383,"remaining_time":0.4020511451},
{"learn":[0.01692948801],"iteration":639,"passed_time":0.7126734201,"remaining_time":0.4008787988},
{"learn":[0.01690360022],"iteration":640,"passed_time":0.713838455,"remaining_time":0.3997940801},
{"learn":[0.01687850705],"iteration":641,"passed_time":0.7150262409,"remaining_time":0.3987217979},
{"learn":[0.01685725515],"iteration":642,"passed_time":0.7161158944,"remaining_time":0.3975946723},
{"learn":[0.01682288831],"iteration":643,"passed_time":0.7171412466,"remaining_time":0.3964321177},
{"learn":[0.01678536994],"iteration":644,"passed_time":0.7181785489,"remaining_time":0.3952765657},
{"learn":[0.01675235406],"iteration":645,"passed_time":0.719198671,"remaining_time":0.3941119652},
{"learn":[0.01670868245],"iteration":646,"passed_time":0.7203268153,"remaining_time":0.3930067478},
{"learn":[0.01665496767],"iteration":647,"passed_time":0.7213621577,"remaining_time":0.3918510486},
{"learn":[0.01661680961],"iteration":648,"passed_time":0.7223800396,"remaining_time":0.3906862772},
{"learn":[0.01657783902],"iteration":649,"passed_time":0.723417112,"remaining_time":0.3895322911},
{"learn":[0.01653494],"iteration":650,"passed_time":0.7244725648,"remaining_time":0.3883885179},
{"learn":[0.0165018437],"iteration":651,"passed_time":0.725498687,"remaining_time":0.3872293605},
{"learn":[0.01648859027],"iteration":652,"passed_time":0.7265829004,"remaining_time":0.38610148},
{"learn":[0.01642304976],"iteration":653,"passed_time":0.727630043,"remaining_time":0.3849541206},
{"learn":[0.01640179084],"iteration":654,"passed_time":0.7286775156,"remaining_time":0.383807241},
{"learn":[0.01637171544],"iteration":655,"passed_time":0.7298436105,"remaining_time":0.3827228689},
{"learn":[0.01635514512],"iteration":656,"passed_time":0.7309661247,"remaining_time":0.3816154959},
{"learn":[0.01632686333],"iteration":657,"passed_time":0.7320816488,"remaining_time":0.3805044436},
{"learn":[0.01629921016],"iteration":658,"passed_time":0.7331252213,"remaining_time":0.3793561464},
{"learn":[0.01627766314],"iteration":659,"passed_time":0.7341254029,"remaining_time":0.3781858136},
{"learn":[0.01624753888],"iteration":660,"passed_time":0.7356078352,"remaining_time":0.3772633224},
{"learn":[0.01622078217],"iteration":661,"passed_time":0.7368589988,"remaining_time":0.3762210598},
{"learn":[0.01618716775],"iteration":662,"passed_time":0.7378533203,"remaining_time":0.3750476153},
{"learn":[0.01616661997],"iteration":663,"passed_time":0.7388442917,"remaining_time":0.3738730151},
{"learn":[0.01613574286],"iteration":664,"passed_time":0.7398120425,"remaining_time":0.3726872696},
{"learn":[0.01610778226],"iteration":665,"passed_time":0.7407876036,"remaining_time":0.3715060955},
{"learn":[0.01607340604],"iteration":666,"passed_time":0.7417897752,"remaining_time":0.3703388233},
{"learn":[0.01605413178],"iteration":667,"passed_time":0.7427583561,"remaining_time":0.3691553507},
{"learn":[0.01602539548],"iteration":668,"passed_time":0.7437543677,"remaining_time":0.3679860922},
{"learn":[0.01600825003],"iteration":669,"passed_time":0.7448718749,"remaining_time":0.3668771921},
{"learn":[0.01597533282],"iteration":670,"passed_time":0.7459147474,"remaining_time":0.365731672},
{"learn":[0.01595099358],"iteration":671,"passed_time":0.7469671202,"remaining_time":0.3645910944},
{"learn":[0.01590827555],"iteration":672,"passed_time":0.7479668017,"remaining_time":0.3634251771},
{"learn":[0.01588151694],"iteration":673,"passed_time":0.7489547031,"remaining_time":0.3622540552},
{"learn":[0.01584973826],"iteration":674,"passed_time":0.749970075,"remaining_time":0.3610967028},
{"learn":[0.01582455951],"iteration":675,"passed_time":0.751034368,"remaining_time":0.3599632178},
{"learn":[0.01578000893],"iteration":676,"passed_time":0.7520644002,"remaining_time":0.3588135912},
{"learn":[0.0157363542],"iteration":677,"passed_time":0.7530516915,"remaining_time":0.3576440187},
{"learn":[0.01571526845],"iteration":678,"passed_time":0.7541002141,"remaining_time":0.3565039304},
{"learn":[0.01569296845],"iteration":679,"passed_time":0.7550889555,"remaining_time":0.3553359791},
{"learn":[0.01565401674],"iteration":680,"passed_time":0.7560934072,"remaining_time":0.3541759132},
{"learn":[0.01561238324],"iteration":681,"passed_time":0.7570716983,"remaining_time":0.3530041057},
{"learn":[0.01557633798],"iteration":682,"passed_time":0.7580631197,"remaining_time":0.3518389589},
{"learn":[0.01554304159],"iteration":683,"passed_time":0.7590563011,"remaining_time":0.3506751333},
{"learn":[0.01550544971],"iteration":684,"passed_time":0.7600881937,"remaining_time":0.3495296073},
{"learn":[0.01547559121],"iteration":685,"passed_time":0.7612493488,"remaining_time":0.3484435795},
{"learn":[0.01544078092],"iteration":686,"passed_time":0.7623051216,"remaining_time":0.3473093203},
{"learn":[0.01541223978],"iteration":687,"passed_time":0.7633882049,"remaining_time":0.3461876743},
{"learn":[0.01539118121],"iteration":688,"passed_time":0.7643970167,"remaining_time":0.3450326157},
{"learn":[0.01534288763],"iteration":689,"passed_time":0.7654073885,"remaining_time":0.3438786818},
{"learn":[0.01531640546],"iteration":690,"passed_time":0.76640424,"remaining_time":0.3427191175},
{"learn":[0.01526680528],"iteration":691,"passed_time":0.7673960715,"remaining_time":0.341557789},
{"learn":[0.01523895016],"iteration":692,"passed_time":0.7683878529,"remaining_time":0.3403969276},
{"learn":[0.01521869123],"iteration":693,"passed_time":0.7693864544,"remaining_time":0.3392395606},
{"learn":[0.01517837192],"iteration":694,"passed_time":0.7703704357,"remaining_time":0.3380762344},
{"learn":[0.01514904527],"iteration":695,"passed_time":0.771360507,"remaining_time":0.3369160835},
{"learn":[0.01511804559],"iteration":696,"passed_time":0.772379029,"remaining_time":0.3357687888},
{"learn":[0.01508839669],"iteration":697,"passed_time":0.7733764506,"remaining_time":0.3346127336},
{"learn":[0.01506021082],"iteration":698,"passed_time":0.7743846323,"remaining_time":0.3334617659},
{"learn":[0.01503489049],"iteration":699,"passed_time":0.7753766637,"remaining_time":0.3323042845},
{"learn":[0.01501456046],"iteration":700,"passed_time":0.7764429865,"remaining_time":0.3311789628},
{"learn":[0.01498622077],"iteration":701,"passed_time":0.7776105217,"remaining_time":0.3300967742},
{"learn":[0.0149594057],"iteration":702,"passed_time":0.7786663648,"remaining_time":0.3289671555},
{